{
  "name": "Trader",
  "fields": [
    {
      "fieldName": "name",
      "fieldType": "String",
      "fieldValidateRules": ["required"]
    },
    {
      "fieldName": "owner",
      "fieldType": "String",
      "fieldValidateRules": ["required"]
    },
    {
      "fieldName": "market",
      "fieldType": "MARKET",
      "fieldValues": "SAMPLE_ENUM",
      "fieldValidateRules": ["required"]
    },
    {
      "fieldName": "symbol",
      "fieldType": "SYMBOL",
      "fieldValues": "SAMPLE_SYMBOL",
      "fieldValidateRules": ["required"]
    },
    {
      "fieldName": "apiKey",
      "fieldType": "String",
      "fieldValidateRules": ["required"]
    },
    {
      "fieldName": "apiSecret",
      "fieldType": "String",
      "fieldValidateRules": ["required"]
    },
    {
      "fieldName": "isLive",
      "fieldType": "Boolean",
      "fieldValidateRules": ["required"]
    },
    {
      "fieldName": "isIn",
      "fieldType": "Boolean",
      "fieldValidateRules": ["required"]
    },
    {
      "fieldName": "budget",
      "fieldType": "Double",
      "fieldValidateRules": ["required"]
    }
  ],
  "relationships": [],
  "changelogDate": "20200525192051",
  "javadoc": "The Trader entity.\\n@author A true hipster",
  "entityTableName": "trader",
  "dto": "mapstruct",
  "pagination": "no",
  "service": "serviceClass",
  "jpaMetamodelFiltering": false,
  "fluentMethods": true,
  "readOnly": false,
  "embedded": false,
  "clientRootFolder": "",
  "applications": ["tradingService"],
  "microserviceName": "tradingService"
}
